csp/Transpiler.py
csp/csp.py
csp_lang-2.0.1.dist-info/licenses/LICENSE
csp_lang-2.0.1.dist-info/METADATA
csp_lang-2.0.1.dist-info/WHEEL
csp_lang-2.0.1.dist-info/entry_points.txt
csp_lang-2.0.1.dist-info/top_level.txt
csp_lang-2.0.1.dist-info/RECORD
