Metadata-Version: 2.4
Name: csp_lang
Version: 2.0.1
Summary: Custom Syntax for Python Language -- CSPLang
Author-email: Muhammad Abubakar Siddique Ansari <ansaricodes@gmail.com>
Project-URL: Homepage, https://github.com/Ansari-Codes/custom-syntax-for-python.git
Requires-Python: >=3.5
License-File: LICENSE
Dynamic: license-file
